smosaic/__init__.py
smosaic/smosaic_clip_raster.py
smosaic/smosaic_collection_get_data.py
smosaic/smosaic_collection_query.py
smosaic/smosaic_count_pixels.py
smosaic/smosaic_download_stream.py
smosaic/smosaic_filter_scenes.py
smosaic/smosaic_fix_baseline_number.py
smosaic/smosaic_generate_cog.py
smosaic/smosaic_get_dataset_extents.py
smosaic/smosaic_merge_scene.py
smosaic/smosaic_merge_tifs.py
smosaic/smosaic_mosaic.py
smosaic/smosaic_reproject_tif.py
smosaic/smosaic_spectral_indices.py
smosaic/smosaic_utils.py
smosaic/config/br_states.json
smosaic/config/grids.json
smosaic-0.6.dist-info/licenses/LICENSE
smosaic-0.6.dist-info/METADATA
smosaic-0.6.dist-info/WHEEL
smosaic-0.6.dist-info/top_level.txt
smosaic-0.6.dist-info/RECORD
