Metadata-Version: 2.4
Name: smosaic
Version: 0.6
Summary: Simple python package for creating satellite image mosaics based on Brazil Data Cube
Home-page: https://github.com/GSansigolo/smosaic
Author: Gabriel Sansigolo
Author-email: gabrielsansigolo@gmail.com
License-File: LICENSE
Requires-Dist: numpy==2.3.4
Requires-Dist: tqdm==4.67.1
Requires-Dist: pyproj==3.7.2
Requires-Dist: shapely==2.1.2
Requires-Dist: requests==2.32.5
Requires-Dist: rasterio==1.4.3
Requires-Dist: pystac-client==0.9.0
Dynamic: author
Dynamic: author-email
Dynamic: description
Dynamic: home-page
Dynamic: license-file
Dynamic: requires-dist
Dynamic: summary
